farmlayers/__init__.py
farmlayers/download_inputs.py
farmlayers/inspect.py
farmlayers/read_boundaries.py
farmlayers-0.0.3.dist-info/LICENSE
farmlayers-0.0.3.dist-info/METADATA
farmlayers-0.0.3.dist-info/WHEEL
farmlayers-0.0.3.dist-info/top_level.txt
farmlayers-0.0.3.dist-info/RECORD
