Metadata-Version: 2.1
Name: farmlayers
Version: 0.0.3
Summary: Helper scripts for fetching and managing basic input layers Farm Mapping
Home-page: https://github.com/Open-Source-Agriculture/farmlayers
Author: Kipling Crossing
Author-email: kip.crossing@gmail.com
License: UNKNOWN
Platform: UNKNOWN
Classifier: Programming Language :: Python :: 3
Classifier: License :: OSI Approved :: Apache Software License
Classifier: Operating System :: OS Independent
Requires-Python: >=3.7
Requires-Dist: Pillow
Requires-Dist: Shapely (==1.*)
Requires-Dist: elevation
Requires-Dist: geojson
Requires-Dist: geotiff (==0.1.*)
Requires-Dist: imagecodecs
Requires-Dist: numpy
Requires-Dist: pylandsat (==0.6.*)
Requires-Dist: pyshp (==2.*)
